figpack/__init__.py
figpack/cli.py
figpack/extensions.py
figpack/core/__init__.py
figpack/core/_bundle_utils.py
figpack/core/_figure_utils.py
figpack/core/_file_handler.py
figpack/core/_patch_figure.py
figpack/core/_revert_patch_figure.py
figpack/core/_save_figure.py
figpack/core/_server_manager.py
figpack/core/_show_view.py
figpack/core/_upload_bundle.py
figpack/core/_view_figure.py
figpack/core/_zarr_consolidate.py
figpack/core/config.py
figpack/core/extension_view.py
figpack/core/figpack_extension.py
figpack/core/figpack_view.py
figpack/core/zarr.py
figpack/figpack-figure-dist/index.html
figpack/figpack-figure-dist/assets/index-CeJiyHt4.js
figpack/figpack-figure-dist/assets/index-GPjx4QpG.css
figpack/figpack-figure-dist/assets/neurosift-logo-CLsuwLMO.png
figpack/utils/__init__.py
figpack/views/Box.py
figpack/views/CaptionedView.py
figpack/views/DataFrame.py
figpack/views/Gallery.py
figpack/views/GalleryItem.py
figpack/views/Iframe.py
figpack/views/Image.py
figpack/views/LayoutItem.py
figpack/views/Markdown.py
figpack/views/MatplotlibFigure.py
figpack/views/MountainLayout.py
figpack/views/MountainLayoutItem.py
figpack/views/MultiChannelTimeseries.py
figpack/views/Spectrogram.py
figpack/views/Splitter.py
figpack/views/TabLayout.py
figpack/views/TabLayoutItem.py
figpack/views/TimeseriesGraph.py
figpack/views/VerticalLayout.py
figpack/views/VerticalLayoutItem.py
figpack/views/__init__.py
figpack/views/PlotlyExtension/PlotlyExtension.py
figpack/views/PlotlyExtension/__init__.py
figpack/views/PlotlyExtension/_plotly_extension.py
figpack/views/PlotlyExtension/plotly_view.js
figpack-0.3.15.dist-info/licenses/LICENSE
figpack-serve/worker/container/app.py
figpack-0.3.15.dist-info/METADATA
figpack-0.3.15.dist-info/WHEEL
figpack-0.3.15.dist-info/entry_points.txt
figpack-0.3.15.dist-info/top_level.txt
figpack-0.3.15.dist-info/RECORD
